yfscreen/__init__.py
yfscreen/screen.py
yfscreen/data/categoryname.csv
yfscreen/data/errors.csv
yfscreen/data/exchange.csv
yfscreen/data/filters.csv
yfscreen/data/fundfamilyname.csv
yfscreen/data/industry.csv
yfscreen/data/peer_group.csv
yfscreen/data/region.csv
yfscreen/data/sector.csv
yfscreen-0.1.2.dist-info/METADATA
yfscreen-0.1.2.dist-info/WHEEL
yfscreen-0.1.2.dist-info/top_level.txt
yfscreen-0.1.2.dist-info/RECORD
