Metadata-Version: 2.4
Name: yfscreen
Version: 0.1.2
Summary: Simple and efficient access to Yahoo Finance's 'screener' API <https://finance.yahoo.com/research-hub/screener/> for querying and retrieval of financial data.
Author-email: Jason Foster <jason.j.foster@gmail.com>
License: MIT
Project-URL: Homepage, https://github.com/jasonjfoster/screen
Project-URL: Documentation, https://github.com/jasonjfoster/screen/tree/main/python#readme
Project-URL: Source, https://github.com/jasonjfoster/screen/tree/main/python
Project-URL: Issues, https://github.com/jasonjfoster/screen/issues
Keywords: finance,yahoo,screener,data,equities,mutual funds,etfs,indices,futures
Classifier: Development Status :: 4 - Beta
Classifier: Intended Audience :: Developers
Classifier: Intended Audience :: Financial and Insurance Industry
Classifier: Topic :: Office/Business :: Financial
Classifier: License :: OSI Approved :: MIT License
Classifier: Programming Language :: Python :: 3
Classifier: Programming Language :: Python :: 3.7
Classifier: Programming Language :: Python :: 3.8
Classifier: Programming Language :: Python :: 3.9
Classifier: Programming Language :: Python :: 3.10
Classifier: Operating System :: OS Independent
Requires-Dist: requests>=2.2.0
Requires-Dist: pandas>=1.0.0
Requires-Dist: importlib-resources; python_version < "3.9"
